gnu_screen/__init__.py
gnu_screen-0.0.8.dist-info/METADATA
gnu_screen-0.0.8.dist-info/WHEEL
gnu_screen-0.0.8.dist-info/top_level.txt
gnu_screen-0.0.8.dist-info/RECORD
