Metadata-Version: 2.1
Name: gnu-screen
Version: 0.0.8
Summary: GNU-Screen session module handler for NodeJs
Home-page: https://github.com/LoucasMaillet/Lib-GNU-Screen/tree/main/Python
Author: Lucas Maillet
Author-email: loucas.maillet.pro@gmail.com
License: UNKNOWN
Project-URL: Bug Tracker, https://github.com/LoucasMaillet/Lib-GNU-Screen/issues
Platform: UNKNOWN
Classifier: Programming Language :: Python :: 3
Classifier: License :: OSI Approved :: GNU General Public License v3 (GPLv3)
Classifier: Operating System :: Unix
Classifier: Operating System :: Microsoft :: Windows
Requires-Python: >=3
